pz_rekormonitor/artifact.bundle
pz_rekormonitor/artifact.md
pz_rekormonitor/main.py
pz_rekormonitor/merkle_proof.py
pz_rekormonitor/util.py
pz_rekormonitor-0.4.0.dist-info/METADATA
pz_rekormonitor-0.4.0.dist-info/WHEEL
pz_rekormonitor-0.4.0.dist-info/entry_points.txt
pz_rekormonitor-0.4.0.dist-info/RECORD
