Metadata-Version: 2.1
Name: pz_rekormonitor
Version: 0.4.0
Summary: 
Requires-Python: >=3.12,<4.0
Classifier: Programming Language :: Python :: 3
Classifier: Programming Language :: Python :: 3.12
Classifier: Programming Language :: Python :: 3.13
Requires-Dist: cryptography (>=44.0.0,<45.0.0)
Requires-Dist: jsonschema (>=4.23.0,<5.0.0)
Requires-Dist: requests (>=2.32.3,<3.0.0)
